ucdeconvolve/__init__.py
ucdeconvolve/_data.py
ucdeconvolve/_exceptions.py
ucdeconvolve/_io.py
ucdeconvolve/_metadata.py
ucdeconvolve/_postprocessing.py
ucdeconvolve/_propagator.py
ucdeconvolve/_settings.py
ucdeconvolve/_utils.py
ucdeconvolve/_api/__init__.py
ucdeconvolve/_api/_api.py
ucdeconvolve/_api/_apiutils.py
ucdeconvolve/_api/_statewatchers.py
ucdeconvolve/_compat/__init__.py
ucdeconvolve/_compat/_tools.py
ucdeconvolve/_plotting/__init__.py
ucdeconvolve/_plotting/_base_plotting.py
ucdeconvolve/_plotting/_colormaps.py
ucdeconvolve/_plotting/_common_plotting.py
ucdeconvolve/_plotting/_explain_plotting.py
ucdeconvolve/_plotting/_plotting.py
ucdeconvolve/_plotting/_plotutils.py
ucdeconvolve/_tools/__init__.py
ucdeconvolve/_tools/_base.py
ucdeconvolve/_tools/_explain.py
ucdeconvolve/_tools/_select.py
ucdeconvolve/_tools/_tools.py
ucdeconvolve/_utilities/__init__.py
ucdeconvolve/_utilities/_utilities_common.py
ucdeconvolve/data/metadata.pkl
ucdeconvolve-0.1.2.dist-info/LICENSE
ucdeconvolve-0.1.2.dist-info/METADATA
ucdeconvolve-0.1.2.dist-info/WHEEL
ucdeconvolve-0.1.2.dist-info/top_level.txt
ucdeconvolve-0.1.2.dist-info/RECORD
