Metadata-Version: 2.1
Name: ucdeconvolve
Version: 0.1.2
Summary: Cell Type Deconvolution For Transcriptomic Data
Home-page: https://github.com/dchary/ucdeconvolve
Author: Daniel Charytonowicz
Author-email: daniel.charytonowicz@icahn.mssm.edu
License: GNU GPLv3
License-File: LICENSE
Requires-Dist: anndata (>=0.7.8)
Requires-Dist: scanpy (>=1.8.2)
Requires-Dist: pandas (>=1.3.5)
Requires-Dist: numpy (>=1.21.6)
Requires-Dist: progressbar2 (>=4.0.0)
Requires-Dist: numba (>=0.55.2)
Requires-Dist: scikit-learn (>=1.0.2)
Requires-Dist: networkx (>=2.6.3)
Requires-Dist: seaborn (>=0.11.2)
Requires-Dist: urllib3 (>=1.26.8)
Requires-Dist: requests (>2.27.1)
Requires-Dist: mudata (>=0.2.1)
Requires-Dist: click (>=8.0.4)
Requires-Dist: hdf5plugin (>=4.1.1)
Requires-Dist: more-itertools (>=8.12.0)
Requires-Dist: textwrap3 (>=0.9.2)
Requires-Dist: chardet (>=4.0.0)
Requires-Dist: tables (>=3.7.0)
